devdice/__init__.py
devdice/devdice.py
devdice-0.0.5.dist-info/licenses/LICENSE
tests/test_chooser.py
tests/test_eliminator.py
tests/test_flip_a_coin.py
tests/test_magic_eight_ball.py
tests/test_random_color_generator.py
tests/test_rock_paper_scissors.py
tests/test_roll_a_dice.py
tests/test_roulette.py
devdice-0.0.5.dist-info/METADATA
devdice-0.0.5.dist-info/WHEEL
devdice-0.0.5.dist-info/entry_points.txt
devdice-0.0.5.dist-info/top_level.txt
devdice-0.0.5.dist-info/RECORD
