Metadata-Version: 2.4
Name: devdice
Version: 0.0.5
Summary: A package developed with pipenv, built with build using setuptools, uploaded to PyPI using twine, and distributed via pip.
Author: Benjamin DeWeese, Forrest Williams, John Ma, Edwin Chen
License:                     GNU GENERAL PUBLIC LICENSE
Project-URL: Assignment Page, https://github.com/nyu-software-engineering/python-package-example
Project-URL: Repository, https://github.com/software-students-spring2025/3-python-package-four-locals
Project-URL: Bug Tracker, https://github.com/software-students-spring2025/3-python-package-four-locals/issues
Keywords: python,package,build,tutorial
Classifier: Programming Language :: Python :: 3
Classifier: Intended Audience :: Education
Classifier: License :: OSI Approved :: GNU General Public License v3 (GPLv3)
Classifier: Operating System :: OS Independent
Requires-Python: >=3.7
License-File: LICENSE
Provides-Extra: dev
Requires-Dist: pytest; extra == "dev"
Dynamic: license-file
